Workbook

Sheet Role Families
A1: # | B1: Role Family | C1: P1 (Default) | D1: P2 (Default) | E1: P3 (Default) | F1: Why P1 matters most | G1: Example Roles
A2: 1 | B2: Marketing / Brand | C2: Industry | D2: Platform | E2: Model | F2: Marketers must understand the customer, product claims, and regulatory landscape of their specific industry | G2: CMO, VP Marketing, Head of Brand, Director of Growth, VP Digital Marketing, Head of Content
A3: 2 | B3: Finance / Accounting | C3: Platform | D3: Model | E3: Industry | F3: Finance leaders need to understand how money flows — revenue recognition, unit economics, and financial operations depend on the transaction platform | G3: CFO, VP Finance, Controller, Treasurer, Head of FP&A, Director of Accounting
A4: 3 | B4: Sales / Revenue | C4: Model | D4: Industry | E4: Platform | F4: The business model defines the entire sales motion — subscription retention vs ad-hoc conversion vs marketplace growth are fundamentally different | G4: CRO, VP Sales, Head of BD, CCO, VP Partnerships, Director of Account Management
A5: 4 | B5: Operations / General Mgmt | C5: Platform | D5: Model | E5: Industry | F5: Operations leaders manage the platform complexity — multi-unit stores, warehouses, digital fulfillment, or field services | G5: COO, President, GM, CEO, Chief of Staff, VP Operations
A6: 5 | B6: People / HR | C6: Industry | D6: Model | E6: Platform | F6: HR needs to understand the industry talent pool — where to recruit, comp benchmarks, and culture norms differ by industry | G6: CHRO, VP People, Head of Talent, VP HR, Director of People Ops
A7: 6 | B7: Technology / Engineering | C7: Platform | D7: Industry | E7: Model | F7: Tech leaders build and maintain the platform — DTC stack vs POS systems vs marketplace infrastructure require different expertise | G7: CTO, VP Engineering, Head of Product Engineering, Director of IT
A8: 7 | B8: Product | C8: Platform | D8: Industry | E8: Model | F8: Product leaders shape the customer experience which is defined by the transaction platform — mobile app, physical store, or omnichannel | G8: CPO, VP Product, Head of Product, Director of Product Management
A9: 8 | B9: Supply Chain / Logistics | C9: Model | D9: Platform | E9: Industry | F9: Business model dictates supply chain design — subscription = predictable demand, ad-hoc = variable, marketplace = no inventory | G9: VP Supply Chain, Head of Logistics, Director of Procurement, VP Manufacturing
A10: 9 | B10: Legal / Compliance | C10: Industry | D10: Model | E10: Platform | F10: Legal/compliance landscape is heavily industry-specific — food safety vs fintech regulations vs healthcare HIPAA | G10: General Counsel, CLO, VP Legal, Head of Regulatory, Chief Compliance Officer
A11: 10 | B11: Data / Analytics | C11: Platform | D11: Model | E11: Industry | F11: Data leaders need platform context — DTC generates different data patterns than four-wall retail or marketplace | G11: CDO, VP Data, Head of Analytics, Director of Data Science

Sheet Tiers
A1: Vector | B1: Tier | C1: Value | D1: Description
A2: Business Model | B2: Common | C2: Subscription | D2: Recurring revenue from regular payments
A3: Business Model | B3: Common | C3: E-Commerce | D3: Online buying and selling
A4: Business Model | B4: Common | C4: SaaS | D4: Software as a service, recurring license
A5: Business Model | B5: Common | C5: Retail | D5: Physical store sales
A6: Business Model | B6: Common | C6: Wholesale | D6: Bulk sales to retailers/distributors
A7: Business Model | B7: Common | C7: Ad Hoc Commerce | D7: Walk-in, one-time transactions (QSR, coffee)
A8: Business Model | B8: Common | C8: Franchise | D8: License-based expansion through operators
A9: Business Model | B9: Common | C9: Marketplace | D9: Platform connecting buyers and sellers
A10: Business Model | B10: Common | C10: Revenue Share | D10: Split revenue with partners
A11: Business Model | B11: Common | C11: Freemium | D11: Free tier with paid upgrades
A12: Business Model | B12: Common | C12: Membership | D12: Fee-based access to services
... A61: Transaction Platform | B61: Unique | C61: Peer-to-peer Network | D61: Users transact directly with each other — lending, energy, services

Sheet Validation
A1: # | B1: Company | C1: Industry | D1: Business Model | E1: Transaction Platform | F1: Role | G1: Role Family | H1: Model Tier | I1: Industry Tier | J1: Platform Tier | K1: P1 | L1: P2 | M1: P3
A2: 1 | B2: Ollie | C2: Pet Food | D2: Subscription | E2: Digital DTC | F2: CFO | G2: Finance / Accounting | H2: Common | I2: Common | J2: Common | K2: =IF(NOT(OR(H2="Unique",I2="Unique",J2="Unique")),VLOOKUP(G2,'Role Families'!B:E,2,FALSE),IF(IF(VLOOKUP(G2,'Role Families'!B:E,2,FALSE)="Model",H2,IF(VLOOKUP(G2,'Role Families'!B:E,2,FALSE)="Industry",I2,J2))="Unique",VLOOKUP(G2,'Role Families'!B:E,2,FALSE),IF(IF(VLOOKUP(G2,'Role Families'!B:E,3,FALSE)="Model",H2,IF(VLOOKUP(G2,'Role Families'!B:E,3,FALSE)="Industry",I2,J2))="Unique",VLOOKUP(G2,'Role Families'!B:E,3,FALSE),VLOOKUP(G2,'Role Families'!B:E,4,FALSE)))) | L2: =IF(NOT(OR(H2="Unique",I2="Unique",J2="Unique")),VLOOKUP(G2,'Role Families'!B:E,3,FALSE),IF(IF(VLOOKUP(G2,'Role Families'!B:E,2,FALSE)="Model",H2,IF(VLOOKUP(G2,'Role Families'!B:E,2,FALSE)="Industry",I2,J2))="Unique",VLOOKUP(G2,'Role Families'!B:E,3,FALSE),VLOOKUP(G2,'Role Families'!B:E,2,FALSE))) | M2: =IF(NOT(OR(H2="Unique",I2="Unique",J2="Unique")),VLOOKUP(G2,'Role Families'!B:E,4,FALSE),IF(IF(VLOOKUP(G2,'Role Families'!B:E,2,FALSE)="Model",H2,IF(VLOOKUP(G2,'Role Families'!B:E,2,FALSE)="Industry",I2,J2))="Unique",VLOOKUP(G2,'Role Families'!B:E,4,FALSE),IF(IF(VLOOKUP(G2,'Role Families'!B:E,3,FALSE)="Model",H2,IF(VLOOKUP(G2,'Role Families'!B:E,3,FALSE)="Industry",I2,J2))="Unique",VLOOKUP(G2,'Role Families'!B:E,4,FALSE),VLOOKUP(G2,'Role Families'!B:E,3,FALSE))))
A3: 2 | B3: The Farmer's Dog | C3: Pet Food | D3: Subscription | E3: Digital DTC | F3: CMO | G3: Marketing / Brand | H3: Common | I3: Common | J3: Common | K3: =IF(NOT(OR(H3="Unique",I3="Unique",J3="Unique")),VLOOKUP(G3,'Role Families'!B:E,2,FALSE),IF(IF(VLOOKUP(G3,'Role Families'!B:E,2,FALSE)="Model",H3,IF(VLOOKUP(G3,'Role Families'!B:E,2,FALSE)="Industry",I3,J3))="Unique",VLOOKUP(G3,'Role Families'!B:E,2,FALSE),IF(IF(VLOOKUP(G3,'Role Families'!B:E,3,FALSE)="Model",H3,IF(VLOOKUP(G3,'Role Families'!B:E,3,FALSE)="Industry",I3,J3))="Unique",VLOOKUP(G3,'Role Families'!B:E,3,FALSE),VLOOKUP(G3,'Role Families'!B:E,4,FALSE)))) | L3: =IF(NOT(OR(H3="Unique",I3="Unique",J3="Unique")),VLOOKUP(G3,'Role Families'!B:E,3,FALSE),IF(IF(VLOOKUP(G3,'Role Families'!B:E,2,FALSE)="Model",H3,IF(VLOOKUP(G3,'Role Families'!B:E,2,FALSE)="Industry",I3,J3))="Unique",VLOOKUP(G3,'Role Families'!B:E,3,FALSE),VLOOKUP(G3,'Role Families'!B:E,2,FALSE))) | M3: =IF(NOT(OR(H3="Unique",I3="Unique",J3="Unique")),VLOOKUP(G3,'Role Families'!B:E,4,FALSE),IF(IF(VLOOKUP(G3,'Role Families'!B:E,2,FALSE)="Model",H3,IF(VLOOKUP(G3,'Role Families'!B:E,2,FALSE)="Industry",I3,J3))="Unique",VLOOKUP(G3,'Role Families'!B:E,4,FALSE),IF(IF(VLOOKUP(G3,'Role Families'!B:E,3,FALSE)="Model",H3,IF(VLOOKUP(G3,'Role Families'!B:E,3,FALSE)="Industry",I3,J3))="Unique",VLOOKUP(G3,'Role Families'!B:E,4,FALSE),VLOOKUP(G3,'Role Families'!B:E,3,FALSE))))
A4: 3 | B4: Freshpet | C4: Pet Food | D4: Retail (Refrigerated) | E4: Omnichannel | F4: VP Supply Chain | G4: Supply Chain / Logistics | H4: Common | I4: Common | J4: Common | K4: =IF(NOT(OR(H4="Unique",I4="Unique",J4="Unique")),VLOOKUP(G4,'Role Families'!B:E,2,FALSE),IF(IF(VLOOKUP(G4,'Role Families'!B:E,2,FALSE)="Model",H4,IF(VLOOKUP(G4,'Role Families'!B:E,2,FALSE)="Industry",I4,J4))="Unique",VLOOKUP(G4,'Role Families'!B:E,2,FALSE),IF(IF(VLOOKUP(G4,'Role Families'!B:E,3,FALSE)="Model",H4,IF(VLOOKUP(G4,'Role Families'!B:E,3,FALSE)="Industry",I4,J4))="Unique",VLOOKUP(G4,'Role Families'!B:E,3,FALSE),VLOOKUP(G4,'Role Families'!B:E,4,FALSE)))) | L4: =IF(NOT(OR(H4="Unique",I4="Unique",J4="Unique")),VLOOKUP(G4,'Role Families'!B:E,3,FALSE),IF(IF(VLOOKUP(G4,'Role Families'!B:E,2,FALSE)="Model",H4,IF(VLOOKUP(G4,'Role Families'!B:E,2,FALSE)="Industry",I4,J4))="Unique",VLOOKUP(G4,'Role Families'!B:E,3,FALSE),VLOOKUP(G4,'Role Families'!B:E,2,FALSE))) | M4: =IF(NOT(OR(H4="Unique",I4="Unique",J4="Unique")),VLOOKUP(G4,'Role Families'!B:E,4,FALSE),IF(IF(VLOOKUP(G4,'Role Families'!B:E,2,FALSE)="Model",H4,IF(VLOOKUP(G4,'Role Families'!B:E,2,FALSE)="Industry",I4,J4))="Unique",VLOOKUP(G4,'Role Families'!B:E,4,FALSE),IF(IF(VLOOKUP(G4,'Role Families'!B:E,3,FALSE)="Model",H4,IF(VLOOKUP(G4,'Role Families'!B:E,3,FALSE)="Industry",I4,J4))="Unique",VLOOKUP(G4,'Role Families'!B:E,4,FALSE),VLOOKUP(G4,'Role Families'!B:E,3,FALSE))))
A5: 4 | B5: Chewy | C5: Pet Products / E-Commerce | D5: E-Commerce | E5: Digital E-Commerce | F5: CTO | G5: Technology / Engineering | H5: Common | I5: Common | J5: Common | K5: =IF(NOT(OR(H5="Unique",I5="Unique",J5="Unique")),VLOOKUP(G5,'Role Families'!B:E,2,FALSE),IF(IF(VLOOKUP(G5,'Role Families'!B:E,2,FALSE)="Model",H5,IF(VLOOKUP(G5,'Role Families'!B:E,2,FALSE)="Industry",I5,J5))="Unique",VLOOKUP(G5,'Role Families'!B:E,2,FALSE),IF(IF(VLOOKUP(G5,'Role Families'!B:E,3,FALSE)="Model",H5,IF(VLOOKUP(G5,'Role Families'!B:E,3,FALSE)="Industry",I5,J5))="Unique",VLOOKUP(G5,'Role Families'!B:E,3,FALSE),VLOOKUP(G5,'Role Families'!B:E,4,FALSE)))) | L5: =IF(NOT(OR(H5="Unique",I5="Unique",J5="Unique")),VLOOKUP(G5,'Role Families'!B:E,3,FALSE),IF(IF(VLOOKUP(G5,'Role Families'!B:E,2,FALSE)="Model",H5,IF(VLOOKUP(G5,'Role Families'!B:E,2,FALSE)="Industry",I5,J5))="Unique",VLOOKUP(G5,'Role Families'!B:E,3,FALSE),VLOOKUP(G5,'Role Families'!B:E,2,FALSE))) | M5: =IF(NOT(OR(H5="Unique",I5="Unique",J5="Unique")),VLOOKUP(G5,'Role Families'!B:E,4,FALSE),IF(IF(VLOOKUP(G5,'Role Families'!B:E,2,FALSE)="Model",H5,IF(VLOOKUP(G5,'Role Families'!B:E,2,FALSE)="Industry",I5,J5))="Unique",VLOOKUP(G5,'Role Families'!B:E,4,FALSE),IF(IF(VLOOKUP(G5,'Role Families'!B:E,3,FALSE)="Model",H5,IF(VLOOKUP(G5,'Role Families'!B:E,3,FALSE)="Industry",I5,J5))="Unique",VLOOKUP(G5,'Role Families'!B:E,4,FALSE),VLOOKUP(G5,'Role Families'!B:E,3,FALSE))))
A6: 5 | B6: BarkBox | C6: Pet Products | D6: Subscription | E6: Digital DTC | F6: VP Sales | G6: Sales / Revenue | H6: Common | I6: Common | J6: Common | K6: =IF(NOT(OR(H6="Unique",I6="Unique",J6="Unique")),VLOOKUP(G6,'Role Families'!B:E,2,FALSE),IF(IF(VLOOKUP(G6,'Role Families'!B:E,2,FALSE)="Model",H6,IF(VLOOKUP(G6,'Role Families'!B:E,2,FALSE)="Industry",I6,J6))="Unique",VLOOKUP(G6,'Role Families'!B:E,2,FALSE),IF(IF(VLOOKUP(G6,'Role Families'!B:E,3,FALSE)="Model",H6,IF(VLOOKUP(G6,'Role Families'!B:E,3,FALSE)="Industry",I6,J6))="Unique",VLOOKUP(G6,'Role Families'!B:E,3,FALSE),VLOOKUP(G6,'Role Families'!B:E,4,FALSE)))) | L6: =IF(NOT(OR(H6="Unique",I6="Unique",J6="Unique")),VLOOKUP(G6,'Role Families'!B:E,3,FALSE),IF(IF(VLOOKUP(G6,'Role Families'!B:E,2,FALSE)="Model",H6,IF(VLOOKUP(G6,'Role Families'!B:E,2,FALSE)="Industry",I6,J6))="Unique",VLOOKUP(G6,'Role Families'!B:E,3,FALSE),VLOOKUP(G6,'Role Families'!B:E,2,FALSE))) | M6: =IF(NOT(OR(H6="Unique",I6="Unique",J6="Unique")),VLOOKUP(G6,'Role Families'!B:E,4,FALSE),IF(IF(VLOOKUP(G6,'Role Families'!B:E,2,FALSE)="Model",H6,IF(VLOOKUP(G6,'Role Families'!B:E,2,FALSE)="Industry",I6,J6))="Unique",VLOOKUP(G6,'Role Families'!B:E,4,FALSE),IF(IF(VLOOKUP(G6,'Role Families'!B:E,3,FALSE)="Model",H6,IF(VLOOKUP(G6,'Role Families'!B:E,3,FALSE)="Industry",I6,J6))="Unique",VLOOKUP(G6,'Role Families'!B:E,4,FALSE),VLOOKUP(G6,'Role Families'!B:E,3,FALSE))))
A7: 6 | B7: Alo Yoga | C7: Activewear | D7: E-Commerce + Retail | E7: Omnichannel | F7: CMO | G7: Marketing / Brand | H7: Common | I7: Common | J7: Common | K7: =IF(NOT(OR(H7="Unique",I7="Unique",J7="Unique")),VLOOKUP(G7,'Role Families'!B:E,2,FALSE),IF(IF(VLOOKUP(G7,'Role Families'!B:E,2,FALSE)="Model",H7,IF(VLOOKUP(G7,'Role Families'!B:E,2,FALSE)="Industry",I7,J7))="Unique",VLOOKUP(G7,'Role Families'!B:E,2,FALSE),IF(IF(VLOOKUP(G7,'Role Families'!B:E,3,FALSE)="Model",H7,IF(VLOOKUP(G7,'Role Families'!B:E,3,FALSE)="Industry",I7,J7))="Unique",VLOOKUP(G7,'Role Families'!B:E,3,FALSE),VLOOKUP(G7,'Role Families'!B:E,4,FALSE)))) | L7: =IF(NOT(OR(H7="Unique",I7="Unique",J7="Unique")),VLOOKUP(G7,'Role Families'!B:E,3,FALSE),IF(IF(VLOOKUP(G7,'Role Families'!B:E,2,FALSE)="Model",H7,IF(VLOOKUP(G7,'Role Families'!B:E,2,FALSE)="Industry",I7,J7))="Unique",VLOOKUP(G7,'Role Families'!B:E,3,FALSE),VLOOKUP(G7,'Role Families'!B:E,2,FALSE))) | M7: =IF(NOT(OR(H7="Unique",I7="Unique",J7="Unique")),VLOOKUP(G7,'Role Families'!B:E,4,FALSE),IF(IF(VLOOKUP(G7,'Role Families'!B:E,2,FALSE)="Model",H7,IF(VLOOKUP(G7,'Role Families'!B:E,2,FALSE)="Industry",I7,J7))="Unique",VLOOKUP(G7,'Role Families'!B:E,4,FALSE),IF(IF(VLOOKUP(G7,'Role Families'!B:E,3,FALSE)="Model",H7,IF(VLOOKUP(G7,'Role Families'!B:E,3,FALSE)="Industry",I7,J7))="Unique",VLOOKUP(G7,'Role Families'!B:E,4,FALSE),VLOOKUP(G7,'Role Families'!B:E,3,FALSE))))
A8: 7 | B8: Alo Yoga | C8: Activewear | D8: E-Commerce + Retail | E8: Omnichannel | F8: CHRO | G8: People / HR | H8: Common | I8: Common | J8: Common | K8: =IF(NOT(OR(H8="Unique",I8="Unique",J8="Unique")),VLOOKUP(G8,'Role Families'!B:E,2,FALSE),IF(IF(VLOOKUP(G8,'Role Families'!B:E,2,FALSE)="Model",H8,IF(VLOOKUP(G8,'Role Families'!B:E,2,FALSE)="Industry",I8,J8))="Unique",VLOOKUP(G8,'Role Families'!B:E,2,FALSE),IF(IF(VLOOKUP(G8,'Role Families'!B:E,3,FALSE)="Model",H8,IF(VLOOKUP(G8,'Role Families'!B:E,3,FALSE)="Industry",I8,J8))="Unique",VLOOKUP(G8,'Role Families'!B:E,3,FALSE),VLOOKUP(G8,'Role Families'!B:E,4,FALSE)))) | L8: =IF(NOT(OR(H8="Unique",I8="Unique",J8="Unique")),VLOOKUP(G8,'Role Families'!B:E,3,FALSE),IF(IF(VLOOKUP(G8,'Role Families'!B:E,2,FALSE)="Model",H8,IF(VLOOKUP(G8,'Role Families'!B:E,2,FALSE)="Industry",I8,J8))="Unique",VLOOKUP(G8,'Role Families'!B:E,3,FALSE),VLOOKUP(G8,'Role Families'!B:E,2,FALSE))) | M8: =IF(NOT(OR(H8="Unique",I8="Unique",J8="Unique")),VLOOKUP(G8,'Role Families'!B:E,4,FALSE),IF(IF(VLOOKUP(G8,'Role Families'!B:E,2,FALSE)="Model",H8,IF(VLOOKUP(G8,'Role Families'!B:E,2,FALSE)="Industry",I8,J8))="Unique",VLOOKUP(G8,'Role Families'!B:E,4,FALSE),IF(IF(VLOOKUP(G8,'Role Families'!B:E,3,FALSE)="Model",H8,IF(VLOOKUP(G8,'Role Families'!B:E,3,FALSE)="Industry",I8,J8))="Unique",VLOOKUP(G8,'Role Families'!B:E,4,FALSE),VLOOKUP(G8,'Role Families'!B:E,3,FALSE))))
A9: 8 | B9: Vuori | C9: Activewear | D9: E-Commerce + Retail | E9: Omnichannel | F9: CFO | G9: Finance / Accounting | H9: Common | I9: Common | J9: Common | K9: =IF(NOT(OR(H9="Unique",I9="Unique",J9="Unique")),VLOOKUP(G9,'Role Families'!B:E,2,FALSE),IF(IF(VLOOKUP(G9,'Role Families'!B:E,2,FALSE)="Model",H9,IF(VLOOKUP(G9,'Role Families'!B:E,2,FALSE)="Industry",I9,J9))="Unique",VLOOKUP(G9,'Role Families'!B:E,2,FALSE),IF(IF(VLOOKUP(G9,'Role Families'!B:E,3,FALSE)="Model",H9,IF(VLOOKUP(G9,'Role Families'!B:E,3,FALSE)="Industry",I9,J9))="Unique",VLOOKUP(G9,'Role Families'!B:E,3,FALSE),VLOOKUP(G9,'Role Families'!B:E,4,FALSE)))) | L9: =IF(NOT(OR(H9="Unique",I9="Unique",J9="Unique")),VLOOKUP(G9,'Role Families'!B:E,3,FALSE),IF(IF(VLOOKUP(G9,'Role Families'!B:E,2,FALSE)="Model",H9,IF(VLOOKUP(G9,'Role Families'!B:E,2,FALSE)="Industry",I9,J9))="Unique",VLOOKUP(G9,'Role Families'!B:E,3,FALSE),VLOOKUP(G9,'Role Families'!B:E,2,FALSE))) | M9: =IF(NOT(OR(H9="Unique",I9="Unique",J9="Unique")),VLOOKUP(G9,'Role Families'!B:E,4,FALSE),IF(IF(VLOOKUP(G9,'Role Families'!B:E,2,FALSE)="Model",H9,IF(VLOOKUP(G9,'Role Families'!B:E,2,FALSE)="Industry",I9,J9))="Unique",VLOOKUP(G9,'Role Families'!B:E,4,FALSE),IF(IF(VLOOKUP(G9,'Role Families'!B:E,3,FALSE)="Model",H9,IF(VLOOKUP(G9,'Role Families'!B:E,3,FALSE)="Industry",I9,J9))="Unique",VLOOKUP(G9,'Role Families'!B:E,4,FALSE),VLOOKUP(G9,'Role Families'!B:E,3,FALSE))))
A10: 9 | B10: Allbirds | C10: Footwear / Fashion | D10: E-Commerce + Retail | E10: Omnichannel | F10: VP Product | G10: Product | H10: Common | I10: Common | J10: Common | K10: =IF(NOT(OR(H10="Unique",I10="Unique",J10="Unique")),VLOOKUP(G10,'Role Families'!B:E,2,FALSE),IF(IF(VLOOKUP(G10,'Role Families'!B:E,2,FALSE)="Model",H10,IF(VLOOKUP(G10,'Role Families'!B:E,2,FALSE)="Industry",I10,J10))="Unique",VLOOKUP(G10,'Role Families'!B:E,2,FALSE),IF(IF(VLOOKUP(G10,'Role Families'!B:E,3,FALSE)="Model",H10,IF(VLOOKUP(G10,'Role Families'!B:E,3,FALSE)="Industry",I10,J10))="Unique",VLOOKUP(G10,'Role Families'!B:E,3,FALSE),VLOOKUP(G10,'Role Families'!B:E,4,FALSE)))) | L10: =IF(NOT(OR(H10="Unique",I10="Unique",J10="Unique")),VLOOKUP(G10,'Role Families'!B:E,3,FALSE),IF(IF(VLOOKUP(G10,'Role Families'!B:E,2,FALSE)="Model",H10,IF(VLOOKUP(G10,'Role Families'!B:E,2,FALSE)="Industry",I10,J10))="Unique",VLOOKUP(G10,'Role Families'!B:E,3,FALSE),VLOOKUP(G10,'Role Families'!B:E,2,FALSE))) | M10: =IF(NOT(OR(H10="Unique",I10="Unique",J10="Unique")),VLOOKUP(G10,'Role Families'!B:E,4,FALSE),IF(IF(VLOOKUP(G10,'Role Families'!B:E,2,FALSE)="Model",H10,IF(VLOOKUP(G10,'Role Families'!B:E,2,FALSE)="Industry",I10,J10))="Unique",VLOOKUP(G10,'Role Families'!B:E,4,FALSE),IF(IF(VLOOKUP(G10,'Role Families'!B:E,3,FALSE)="Model",H10,IF(VLOOKUP(G10,'Role Families'!B:E,3,FALSE)="Industry",I10,J10))="Unique",VLOOKUP(G10,'Role Families'!B:E,4,FALSE),VLOOKUP(G10,'Role Families'!B:E,3,FALSE))))
A11: 10 | B11: Warby Parker | C11: Eyewear / Fashion | D11: E-Commerce + Retail | E11: Omnichannel | F11: General Counsel | G11: Legal / Compliance | H11: Common | I11: Common | J11: Common | K11: =IF(NOT(OR(H11="Unique",I11="Unique",J11="Unique")),VLOOKUP(G11,'Role Families'!B:E,2,FALSE),IF(IF(VLOOKUP(G11,'Role Families'!B:E,2,FALSE)="Model",H11,IF(VLOOKUP(G11,'Role Families'!B:E,2,FALSE)="Industry",I11,J11))="Unique",VLOOKUP(G11,'Role Families'!B:E,2,FALSE),IF(IF(VLOOKUP(G11,'Role Families'!B:E,3,FALSE)="Model",H11,IF(VLOOKUP(G11,'Role Families'!B:E,3,FALSE)="Industry",I11,J11))="Unique",VLOOKUP(G11,'Role Families'!B:E,3,FALSE),VLOOKUP(G11,'Role Families'!B:E,4,FALSE)))) | L11: =IF(NOT(OR(H11="Unique",I11="Unique",J11="Unique")),VLOOKUP(G11,'Role Families'!B:E,3,FALSE),IF(IF(VLOOKUP(G11,'Role Families'!B:E,2,FALSE)="Model",H11,IF(VLOOKUP(G11,'Role Families'!B:E,2,FALSE)="Industry",I11,J11))="Unique",VLOOKUP(G11,'Role Families'!B:E,3,FALSE),VLOOKUP(G11,'Role Families'!B:E,2,FALSE))) | M11: =IF(NOT(OR(H11="Unique",I11="Unique",J11="Unique")),VLOOKUP(G11,'Role Families'!B:E,4,FALSE),IF(IF(VLOOKUP(G11,'Role Families'!B:E,2,FALSE)="Model",H11,IF(VLOOKUP(G11,'Role Families'!B:E,2,FALSE)="Industry",I11,J11))="Unique",VLOOKUP(G11,'Role Families'!B:E,4,FALSE),IF(IF(VLOOKUP(G11,'Role Families'!B:E,3,FALSE)="Model",H11,IF(VLOOKUP(G11,'Role Families'!B:E,3,FALSE)="Industry",I11,J11))="Unique",VLOOKUP(G11,'Role Families'!B:E,4,FALSE),VLOOKUP(G11,'Role Families'!B:E,3,FALSE))))
A12: 11 | B12: Lululemon | C12: Activewear | D12: Retail + E-Commerce | E12: Omnichannel | F12: VP Engineering | G12: Technology / Engineering | H12: Common | I12: Common | J12: Common | K12: =IF(NOT(OR(H12="Unique",I12="Unique",J12="Unique")),VLOOKUP(G12,'Role Families'!B:E,2,FALSE),IF(IF(VLOOKUP(G12,'Role Families'!B:E,2,FALSE)="Model",H12,IF(VLOOKUP(G12,'Role Families'!B:E,2,FALSE)="Industry",I12,J12))="Unique",VLOOKUP(G12,'Role Families'!B:E,2,FALSE),IF(IF(VLOOKUP(G12,'Role Families'!B:E,3,FALSE)="Model",H12,IF(VLOOKUP(G12,'Role Families'!B:E,3,FALSE)="Industry",I12,J12))="Unique",VLOOKUP(G12,'Role Families'!B:E,3,FALSE),VLOOKUP(G12,'Role Families'!B:E,4,FALSE)))) | L12: =IF(NOT(OR(H12="Unique",I12="Unique",J12="Unique")),VLOOKUP(G12,'Role Families'!B:E,3,FALSE),IF(IF(VLOOKUP(G12,'Role Families'!B:E,2,FALSE)="Model",H12,IF(VLOOKUP(G12,'Role Families'!B:E,2,FALSE)="Industry",I12,J12))="Unique",VLOOKUP(G12,'Role Families'!B:E,3,FALSE),VLOOKUP(G12,'Role Families'!B:E,2,FALSE))) | M12: =IF(NOT(OR(H12="Unique",I12="Unique",J12="Unique")),VLOOKUP(G12,'Role Families'!B:E,4,FALSE),IF(IF(VLOOKUP(G12,'Role Families'!B:E,2,FALSE)="Model",H12,IF(VLOOKUP(G12,'Role Families'!B:E,2,FALSE)="Industry",I12,J12))="Unique",VLOOKUP(G12,'Role Families'!B:E,4,FALSE),IF(IF(VLOOKUP(G12,'Role Families'!B:E,3,FALSE)="Model",H12,IF(VLOOKUP(G12,'Role Families'!B:E,3,FALSE)="Industry",I12,J12))="Unique",VLOOKUP(G12,'Role Families'!B:E,4,FALSE),VLOOKUP(G12,'Role Families'!B:E,3,FALSE))))
A13: 12 | B13: Bombas | C13: Apparel / Socks | D13: E-Commerce | E13: Digital DTC | F13: Head of Data | G13: Data / Analytics | H13: Common | I13: Common | J13: Common | K13: =IF(NOT(OR(H13="Unique",I13="Unique",J13="Unique")),VLOOKUP(G13,'Role Families'!B:E,2,FALSE),IF(IF(VLOOKUP(G13,'Role Families'!B:E,2,FALSE)="Model",H13,IF(VLOOKUP(G13,'Role Families'!B:E,2,FALSE)="Industry",I13,J13))="Unique",VLOOKUP(G13,'Role Families'!B:E,2,FALSE),IF(IF(VLOOKUP(G13,'Role Families'!B:E,3,FALSE)="Model",H13,IF(VLOOKUP(G13,'Role Families'!B:E,3,FALSE)="Industry",I13,J13))="Unique",VLOOKUP(G13,'Role Families'!B:E,3,FALSE),VLOOKUP(G13,'Role Families'!B:E,4,FALSE)))) | L13: =IF(NOT(OR(H13="Unique",I13="Unique",J13="Unique")),VLOOKUP(G13,'Role Families'!B:E,3,FALSE),IF(IF(VLOOKUP(G13,'Role Families'!B:E,2,FALSE)="Model",H13,IF(VLOOKUP(G13,'Role Families'!B:E,2,FALSE)="Industry",I13,J13))="Unique",VLOOKUP(G13,'Role Families'!B:E,3,FALSE),VLOOKUP(G13,'Role Families'!B:E,2,FALSE))) | M13: =IF(NOT(OR(H13="Unique",I13="Unique",J13="Unique")),VLOOKUP(G13,'Role Families'!B:E,4,FALSE),IF(IF(VLOOKUP(G13,'Role Families'!B:E,2,FALSE)="Model",H13,IF(VLOOKUP(G13,'Role Families'!B:E,2,FALSE)="Industry",I13,J13))="Unique",VLOOKUP(G13,'Role Families'!B:E,4,FALSE),IF(IF(VLOOKUP(G13,'Role Families'!B:E,3,FALSE)="Model",H13,IF(VLOOKUP(G13,'Role Families'!B:E,3,FALSE)="Industry",I13,J13))="Unique",VLOOKUP(G13,'Role Families'!B:E,4,FALSE),VLOOKUP(G13,'Role Families'!B:E,3,FALSE))))
... A98: 97 | B98: Opendoor | C98: Real Estate / PropTech | D98: iBuying (Inventory) | E98: Digital Platform | F98: CFO | G98: Finance / Accounting | H98: Unique | I98: Common | J98: Common | K98: =IF(NOT(OR(H98="Unique",I98="Unique",J98="Unique")),VLOOKUP(G98,'Role Families'!B:E,2,FALSE),IF(IF(VLOOKUP(G98,'Role Families'!B:E,2,FALSE)="Model",H98,IF(VLOOKUP(G98,'Role Families'!B:E,2,FALSE)="Industry",I98,J98))="Unique",VLOOKUP(G98,'Role Families'!B:E,2,FALSE),IF(IF(VLOOKUP(G98,'Role Families'!B:E,3,FALSE)="Model",H98,IF(VLOOKUP(G98,'Role Families'!B:E,3,FALSE)="Industry",I98,J98))="Unique",VLOOKUP(G98,'Role Families'!B:E,3,FALSE),VLOOKUP(G98,'Role Families'!B:E,4,FALSE)))) | L98: =IF(NOT(OR(H98="Unique",I98="Unique",J98="Unique")),VLOOKUP(G98,'Role Families'!B:E,3,FALSE),IF(IF(VLOOKUP(G98,'Role Families'!B:E,2,FALSE)="Model",H98,IF(VLOOKUP(G98,'Role Families'!B:E,2,FALSE)="Industry",I98,J98))="Unique",VLOOKUP(G98,'Role Families'!B:E,3,FALSE),VLOOKUP(G98,'Role Families'!B:E,2,FALSE))) | M98: =IF(NOT(OR(H98="Unique",I98="Unique",J98="Unique")),VLOOKUP(G98,'Role Families'!B:E,4,FALSE),IF(IF(VLOOKUP(G98,'Role Families'!B:E,2,FALSE)="Model",H98,IF(VLOOKUP(G98,'Role Families'!B:E,2,FALSE)="Industry",I98,J98))="Unique",VLOOKUP(G98,'Role Families'!B:E,4,FALSE),IF(IF(VLOOKUP(G98,'Role Families'!B:E,3,FALSE)="Model",H98,IF(VLOOKUP(G98,'Role Families'!B:E,3,FALSE)="Industry",I98,J98))="Unique",VLOOKUP(G98,'Role Families'!B:E,4,FALSE),VLOOKUP(G98,'Role Families'!B:E,3,FALSE))))
